insafeConnectToDatabase/__init__.py
insafeConnectToDatabase/cloud-sql-proxy
insafeConnectToDatabase/cloud-sql-proxy-linux
insafeConnectToDatabase/database_close_connection.py
insafeConnectToDatabase/database_open_connection.py
insafeConnectToDatabase/database_query.py
insafeConnectToDatabase/util/__init__.py
insafeConnectToDatabase/util/wait_for_proxy.py
insafeConnectToDatabase-0.6.2.dist-info/METADATA
insafeConnectToDatabase-0.6.2.dist-info/WHEEL
insafeConnectToDatabase-0.6.2.dist-info/top_level.txt
insafeConnectToDatabase-0.6.2.dist-info/RECORD
