Metadata-Version: 2.1
Name: insafeConnectToDatabase
Version: 0.6.2
Summary: A utility to determine the type of permit based on ID
Home-page: https://github.com
Author: khaled.jabari
Author-email: khaled.jabari@cntxt.com
Classifier: Programming Language :: Python :: 3
Classifier: License :: OSI Approved :: MIT License
Classifier: Operating System :: OS Independent
Requires-Python: >=3.7
Requires-Dist: pydantic >=1.10.0
Requires-Dist: psycopg2
